{
    "fluentMethods": true,
    "relationships": [
        {
            "relationshipType": "many-to-one",
            "relationshipName": "author",
            "otherEntityName": "author",
            "otherEntityField": "id"
        },
        {
            "relationshipType": "many-to-one",
            "relationshipName": "publisher",
            "otherEntityName": "publisher",
            "otherEntityField": "id"
        }
    ],
    "fields": [
        {
            "fieldName": "title",
            "fieldType": "String"
        },
        {
            "fieldName": "volume",
            "fieldType": "Long"
        }
    ],
    "changelogDate": "20181030055612",
    "entityTableName": "book",
    "dto": "mapstruct",
    "pagination": "no",
    "service": "serviceImpl",
    "jpaMetamodelFiltering": false,
    "microserviceName": "thymeleafLayout"
}